account_codes_jp/__init__.py
account_codes_jp/__main__.py
account_codes_jp/_blue_return.py
account_codes_jp/_blue_return.yaml
account_codes_jp/_common.py
account_codes_jp/_edinet.py
account_codes_jp/cli.py
account_codes_jp/py.typed
account_codes_jp-0.4.32.dist-info/LICENSE
account_codes_jp-0.4.32.dist-info/METADATA
account_codes_jp-0.4.32.dist-info/WHEEL
account_codes_jp-0.4.32.dist-info/entry_points.txt
account_codes_jp-0.4.32.dist-info/RECORD
