Metadata-Version: 2.3
Name: account-codes-jp
Version: 0.4.32
Summary: e-Tax / EDINETタクソノミ / 青色申告 の勘定科目(コード)表のラッパー (非公式)
License: AGPL-3.0-only
Author: 34j
Author-email: 34j.github@proton.me
Requires-Python: >=3.10,<4.0
Classifier: Development Status :: 2 - Pre-Alpha
Classifier: Intended Audience :: Developers
Classifier: License :: OSI Approved :: GNU Affero General Public License v3
Classifier: Natural Language :: English
Classifier: Operating System :: OS Independent
Classifier: Programming Language :: Python :: 3
Classifier: Programming Language :: Python :: 3.10
Classifier: Programming Language :: Python :: 3.11
Classifier: Programming Language :: Python :: 3.12
Classifier: Programming Language :: Python :: 3.13
Classifier: Topic :: Software Development :: Libraries
Requires-Dist: cyclopts (>=3.9.0,<4.0.0)
Requires-Dist: japanize-matplotlib (>=1.1.3,<2.0.0)
Requires-Dist: matplotlib (>=3.10.1,<4.0.0)
Requires-Dist: networkx (>=3.4.2,<4.0.0)
Requires-Dist: openpyxl (>=3.1.5,<4.0.0)
Requires-Dist: pandas (>=2.2.3,<3.0.0)
Requires-Dist: pykakasi (>=2.3.0,<3.0.0)
Requires-Dist: pyyaml (>=6.0.2,<7.0.0)
Requires-Dist: rapidfuzz (>=3.12.2,<4.0.0)
Requires-Dist: requests-cache (>=1.2.1,<2.0.0)
Requires-Dist: rich (>=13.9.4,<14.0.0)
Requires-Dist: scipy (>=1.15.2,<2.0.0)
Requires-Dist: setuptools (>=75.8.2,<76.0.0)
Requires-Dist: strenum (>=0.4.15,<0.5.0)
Project-URL: Bug Tracker, https://github.com/34j/account-codes-jp/issues
Project-URL: Changelog, https://github.com/34j/account-codes-jp/blob/main/CHANGELOG.md
Project-URL: Documentation, https://account-codes-jp.readthedocs.io
Project-URL: Repository, https://github.com/34j/account-codes-jp
